materials_commons/cli/LICENSE.txt
materials_commons/cli/__init__.py
materials_commons/cli/cloned_project.py
materials_commons/cli/exceptions.py
materials_commons/cli/file_functions.py
materials_commons/cli/functions.py
materials_commons/cli/globus.py
materials_commons/cli/list_objects.py
materials_commons/cli/parser.py
materials_commons/cli/print_formatter.py
materials_commons/cli/sqltable.py
materials_commons/cli/tmp_functions.py
materials_commons/cli/tree_functions.py
materials_commons/cli/treedb.py
materials_commons/cli/user_config.py
materials_commons/cli/subcommands/__init__.py
materials_commons/cli/subcommands/clone.py
materials_commons/cli/subcommands/config.py
materials_commons/cli/subcommands/dataset.py
materials_commons/cli/subcommands/down.py
materials_commons/cli/subcommands/expt.py
materials_commons/cli/subcommands/fetch.py
materials_commons/cli/subcommands/globus.py
materials_commons/cli/subcommands/init.py
materials_commons/cli/subcommands/ls.py
materials_commons/cli/subcommands/mkdir.py
materials_commons/cli/subcommands/mv.py
materials_commons/cli/subcommands/proj.py
materials_commons/cli/subcommands/remote.py
materials_commons/cli/subcommands/rm.py
materials_commons/cli/subcommands/up.py
materials_commons/cli/subcommands/versions.py
materials_commons_cli-2.1.8.dist-info/LICENSE
materials_commons_cli-2.1.8.dist-info/METADATA
materials_commons_cli-2.1.8.dist-info/WHEEL
materials_commons_cli-2.1.8.dist-info/entry_points.txt
materials_commons_cli-2.1.8.dist-info/top_level.txt
materials_commons_cli-2.1.8.dist-info/RECORD
