Metadata-Version: 2.1
Name: materials-commons-cli
Version: 2.1.8
Summary: Materials Commons CLI
Home-page: https://materials-commons.github.io/materials-commons-cli/html/index.html
Author: Materials Commons development team
Author-email: materials-commons-help@umich.edu
License: MIT
Keywords: materials science mc materials-commons prisms
Platform: UNKNOWN
Classifier: Development Status :: 4 - Beta
Classifier: Intended Audience :: Developers
Classifier: Intended Audience :: Science/Research
Classifier: Topic :: Scientific/Engineering :: Information Analysis
Classifier: License :: OSI Approved :: MIT License
Classifier: Programming Language :: Python :: 3
Classifier: Programming Language :: Python :: 3.8
License-File: LICENSE
Requires-Dist: globus-cli
Requires-Dist: globus-sdk
Requires-Dist: igittigitt (==2.1.0)
Requires-Dist: materials-commons-api (>=2.0.1)
Requires-Dist: python-dateutil
Requires-Dist: pyyaml
Requires-Dist: requests
Requires-Dist: setuptools
Requires-Dist: sortedcontainers
Requires-Dist: tabulate
